standings/__init__.py
standings/_match.py
standings/sportstypes.py
standings/standings.py
standings/standingstest.py
standings/teampoint.py
tablecalculation/__init__.py
tablecalculation/_match.py
tablecalculation/sportstypes.py
tablecalculation/tablecalculation.py
tablecalculation/tablecalculationtest.py
tablecalculation/teampoint.py
standings-1.0.4.dist-info/LICENSE.txt
standings-1.0.4.dist-info/METADATA
standings-1.0.4.dist-info/WHEEL
standings-1.0.4.dist-info/top_level.txt
standings-1.0.4.dist-info/RECORD
