Metadata-Version: 2.1
Name: standings
Version: 1.0.4
Summary: Python library to calculate standings for football and handball
Home-page: https://bitbucket.org/mkr5000/py-footballtables
Author: Marco Wilka
Author-email: m.wilka@gmail.com
License: UNKNOWN
Keywords: football soccer handball table match matches fixture fixtures
Platform: UNKNOWN
Classifier: Development Status :: 5 - Production/Stable
Classifier: Intended Audience :: Developers
Classifier: Topic :: Other/Nonlisted Topic
Classifier: License :: OSI Approved :: MIT License
Classifier: Programming Language :: Python :: 2
Classifier: Programming Language :: Python :: 2.7
Classifier: Programming Language :: Python :: 3
Classifier: Programming Language :: Python :: 3.4
Classifier: Programming Language :: Python :: 3.5
Classifier: Programming Language :: Python :: 3.6
Requires-Dist: requests
